Metadata-Version: 2.4
Name: mseep-mcp-blockchain-query
Version: 0.1.2
Summary: MCP server for querying the Bitcoin blockchain
Home-page: 
Author: mseep
Author-email: mseep <support@skydeck.ai>
Maintainer-email: mseep <support@skydeck.ai>
Requires-Python: >=3.6
Requires-Dist: anyio>=4.5.0
Requires-Dist: black>=23.3.0
Requires-Dist: mcp>=1.3.0
Requires-Dist: httpx>=0.24.0
Requires-Dist: click>=8.1.7
Requires-Dist: pytest>=7.0.0
Requires-Dist: pytest-asyncio>=0.21.0
Requires-Dist: starlette>=0.37.2
Requires-Dist: uvicorn>=0.29.0
Dynamic: author
Dynamic: requires-python
